<?xml version='1.0' encoding='utf-8'?>
<annotation verified="no"><folder>model-v2-mina</folder><filename>mina_page_380.webp</filename><path>/Users/syaamil/development/Quran-Bounding/quran-bounding-project/experiments/model-v2-mina/mina_page_380.webp</path><source><database>Unknown</database></source><size><width>1000</width><height>1452</height><depth>3</depth></size><segmented>0</segmented><object><name>ayat_line</name><pose>Unspecified</pose><truncated>0</truncated><difficult>0</difficult><bndbox><xmin>160</xmin><ymin>618</ymin><xmax>908</xmax><ymax>772</ymax></bndbox><confidence>0.9764</confidence></object><object><name>ayat_line</name><pose>Unspecified</pose><truncated>0</truncated><difficult>0</difficult><bndbox><xmin>161</xmin><ymin>772</ymin><xmax>368</xmax><ymax>849</ymax></bndbox><confidence>0.9705</confidence></object><object><name>ayat_line</name><pose>Unspecified</pose><truncated>0</truncated><difficult>0</difficult><bndbox><xmin>161</xmin><ymin>922</ymin><xmax>908</xmax><ymax>1003</ymax></bndbox><confidence>0.9700</confidence></object><object><name>ayat_line</name><pose>Unspecified</pose><truncated>0</truncated><difficult>0</difficult><bndbox><xmin>446</xmin><ymin>230</ymin><xmax>908</xmax><ymax>309</ymax></bndbox><confidence>0.9687</confidence></object><object><name>ayat_line</name><pose>Unspecified</pose><truncated>0</truncated><difficult>0</difficult><bndbox><xmin>161</xmin><ymin>230</ymin><xmax>447</xmax><ymax>309</ymax></bndbox><confidence>0.9687</confidence></object><object><name>ayat_line</name><pose>Unspecified</pose><truncated>0</truncated><difficult>0</difficult><bndbox><xmin>604</xmin><ymin>541</ymin><xmax>908</xmax><ymax>619</ymax></bndbox><confidence>0.9676</confidence></object><object><name>ayat_line</name><pose>Unspecified</pose><truncated>0</truncated><difficult>0</difficult><bndbox><xmin>161</xmin><ymin>1003</ymin><xmax>708</xmax><ymax>1079</ymax></bndbox><confidence>0.9675</confidence></object><object><name>ayat_line</name><pose>Unspecified</pose><truncated>0</truncated><difficult>0</difficult><bndbox><xmin>368</xmin><ymin>772</ymin><xmax>909</xmax><ymax>849</ymax></bndbox><confidence>0.9667</confidence></object><object><name>ayat_line</name><pose>Unspecified</pose><truncated>0</truncated><difficult>0</difficult><bndbox><xmin>161</xmin><ymin>541</ymin><xmax>603</xmax><ymax>619</ymax></bndbox><confidence>0.9660</confidence></object><object><name>ayat_line</name><pose>Unspecified</pose><truncated>0</truncated><difficult>0</difficult><bndbox><xmin>162</xmin><ymin>464</ymin><xmax>859</xmax><ymax>541</ymax></bndbox><confidence>0.9660</confidence></object><object><name>ayat_line</name><pose>Unspecified</pose><truncated>0</truncated><difficult>0</difficult><bndbox><xmin>221</xmin><ymin>849</ymin><xmax>907</xmax><ymax>922</ymax></bndbox><confidence>0.9659</confidence></object><object><name>ayat_line</name><pose>Unspecified</pose><truncated>0</truncated><difficult>0</difficult><bndbox><xmin>708</xmin><ymin>1004</ymin><xmax>909</xmax><ymax>1079</ymax></bndbox><confidence>0.9626</confidence></object><object><name>ayat_line</name><pose>Unspecified</pose><truncated>0</truncated><difficult>0</difficult><bndbox><xmin>161</xmin><ymin>1079</ymin><xmax>747</xmax><ymax>1158</ymax></bndbox><confidence>0.9617</confidence></object><object><name>ayat_line</name><pose>Unspecified</pose><truncated>0</truncated><difficult>0</difficult><bndbox><xmin>162</xmin><ymin>309</ymin><xmax>907</xmax><ymax>388</ymax></bndbox><confidence>0.9612</confidence></object><object><name>ayat_line</name><pose>Unspecified</pose><truncated>0</truncated><difficult>0</difficult><bndbox><xmin>159</xmin><ymin>1158</ymin><xmax>909</xmax><ymax>1317</ymax></bndbox><confidence>0.9597</confidence></object><object><name>ayat_line</name><pose>Unspecified</pose><truncated>0</truncated><difficult>0</difficult><bndbox><xmin>161</xmin><ymin>388</ymin><xmax>908</xmax><ymax>465</ymax></bndbox><confidence>0.9592</confidence></object><object><name>ayat_line</name><pose>Unspecified</pose><truncated>0</truncated><difficult>0</difficult><bndbox><xmin>747</xmin><ymin>1079</ymin><xmax>909</xmax><ymax>1158</ymax></bndbox><confidence>0.9548</confidence></object><object><name>ayat_line</name><pose>Unspecified</pose><truncated>0</truncated><difficult>0</difficult><bndbox><xmin>860</xmin><ymin>464</ymin><xmax>909</xmax><ymax>541</ymax></bndbox><confidence>0.9357</confidence></object><object><name>ayat_line</name><pose>Unspecified</pose><truncated>0</truncated><difficult>0</difficult><bndbox><xmin>161</xmin><ymin>850</ymin><xmax>221</xmax><ymax>922</ymax></bndbox><confidence>0.9281</confidence></object><object><name>ayah_marker</name><pose>Unspecified</pose><truncated>0</truncated><difficult>0</difficult><bndbox><xmin>604</xmin><ymin>562</ymin><xmax>646</xmax><ymax>609</ymax></bndbox><confidence>0.9216</confidence></object><object><name>ayah_marker</name><pose>Unspecified</pose><truncated>0</truncated><difficult>0</difficult><bndbox><xmin>221</xmin><ymin>870</ymin><xmax>263</xmax><ymax>916</ymax></bndbox><confidence>0.9203</confidence></object><object><name>ayah_marker</name><pose>Unspecified</pose><truncated>0</truncated><difficult>0</difficult><bndbox><xmin>708</xmin><ymin>1025</ymin><xmax>749</xmax><ymax>1071</ymax></bndbox><confidence>0.9196</confidence></object><object><name>ayah_marker</name><pose>Unspecified</pose><truncated>0</truncated><difficult>0</difficult><bndbox><xmin>172</xmin><ymin>1256</ymin><xmax>215</xmax><ymax>1302</ymax></bndbox><confidence>0.9180</confidence></object><object><name>ayah_marker</name><pose>Unspecified</pose><truncated>0</truncated><difficult>0</difficult><bndbox><xmin>369</xmin><ymin>794</ymin><xmax>412</xmax><ymax>841</ymax></bndbox><confidence>0.9172</confidence></object><object><name>ayah_marker</name><pose>Unspecified</pose><truncated>0</truncated><difficult>0</difficult><bndbox><xmin>168</xmin><ymin>330</ymin><xmax>211</xmax><ymax>376</ymax></bndbox><confidence>0.9172</confidence></object><object><name>ayah_marker</name><pose>Unspecified</pose><truncated>0</truncated><difficult>0</difficult><bndbox><xmin>860</xmin><ymin>486</ymin><xmax>901</xmax><ymax>533</ymax></bndbox><confidence>0.9142</confidence></object><object><name>ayat_line</name><pose>Unspecified</pose><truncated>0</truncated><difficult>0</difficult><bndbox><xmin>161</xmin><ymin>141</ymin><xmax>912</xmax><ymax>230</ymax></bndbox><confidence>0.9138</confidence></object><object><name>ayah_marker</name><pose>Unspecified</pose><truncated>0</truncated><difficult>0</difficult><bndbox><xmin>447</xmin><ymin>253</ymin><xmax>488</xmax><ymax>300</ymax></bndbox><confidence>0.9132</confidence></object><object><name>ayah_marker</name><pose>Unspecified</pose><truncated>0</truncated><difficult>0</difficult><bndbox><xmin>747</xmin><ymin>1101</ymin><xmax>789</xmax><ymax>1148</ymax></bndbox><confidence>0.9119</confidence></object></annotation>