<?xml version='1.0' encoding='utf-8'?>
<annotation verified="no"><folder>model-v2-mina</folder><filename>mina_page_517.webp</filename><path>/Users/syaamil/development/Quran-Bounding/quran-bounding-project/experiments/model-v2-mina/mina_page_517.webp</path><source><database>Unknown</database></source><size><width>1000</width><height>1452</height><depth>3</depth></size><segmented>0</segmented><object><name>ayat_line</name><pose>Unspecified</pose><truncated>0</truncated><difficult>0</difficult><bndbox><xmin>87</xmin><ymin>616</ymin><xmax>834</xmax><ymax>767</ymax></bndbox><confidence>0.9789</confidence></object><object><name>ayat_line</name><pose>Unspecified</pose><truncated>0</truncated><difficult>0</difficult><bndbox><xmin>89</xmin><ymin>767</ymin><xmax>834</xmax><ymax>921</ymax></bndbox><confidence>0.9781</confidence></object><object><name>ayat_line</name><pose>Unspecified</pose><truncated>0</truncated><difficult>0</difficult><bndbox><xmin>88</xmin><ymin>140</ymin><xmax>835</xmax><ymax>381</ymax></bndbox><confidence>0.9711</confidence></object><object><name>ayat_line</name><pose>Unspecified</pose><truncated>0</truncated><difficult>0</difficult><bndbox><xmin>90</xmin><ymin>922</ymin><xmax>643</xmax><ymax>1003</ymax></bndbox><confidence>0.9699</confidence></object><object><name>ayat_line</name><pose>Unspecified</pose><truncated>0</truncated><difficult>0</difficult><bndbox><xmin>87</xmin><ymin>382</ymin><xmax>630</xmax><ymax>461</ymax></bndbox><confidence>0.9685</confidence></object><object><name>ayat_line</name><pose>Unspecified</pose><truncated>0</truncated><difficult>0</difficult><bndbox><xmin>198</xmin><ymin>1003</ymin><xmax>835</xmax><ymax>1077</ymax></bndbox><confidence>0.9669</confidence></object><object><name>ayat_line</name><pose>Unspecified</pose><truncated>0</truncated><difficult>0</difficult><bndbox><xmin>87</xmin><ymin>461</ymin><xmax>832</xmax><ymax>539</ymax></bndbox><confidence>0.9666</confidence></object><object><name>ayat_line</name><pose>Unspecified</pose><truncated>0</truncated><difficult>0</difficult><bndbox><xmin>88</xmin><ymin>539</ymin><xmax>621</xmax><ymax>616</ymax></bndbox><confidence>0.9654</confidence></object><object><name>ayat_line</name><pose>Unspecified</pose><truncated>0</truncated><difficult>0</difficult><bndbox><xmin>238</xmin><ymin>1154</ymin><xmax>835</xmax><ymax>1234</ymax></bndbox><confidence>0.9642</confidence></object><object><name>ayat_line</name><pose>Unspecified</pose><truncated>0</truncated><difficult>0</difficult><bndbox><xmin>88</xmin><ymin>1076</ymin><xmax>835</xmax><ymax>1154</ymax></bndbox><confidence>0.9636</confidence></object><object><name>ayat_line</name><pose>Unspecified</pose><truncated>0</truncated><difficult>0</difficult><bndbox><xmin>630</xmin><ymin>381</ymin><xmax>835</xmax><ymax>461</ymax></bndbox><confidence>0.9630</confidence></object><object><name>ayat_line</name><pose>Unspecified</pose><truncated>0</truncated><difficult>0</difficult><bndbox><xmin>89</xmin><ymin>1234</ymin><xmax>835</xmax><ymax>1317</ymax></bndbox><confidence>0.9579</confidence></object><object><name>ayat_line</name><pose>Unspecified</pose><truncated>0</truncated><difficult>0</difficult><bndbox><xmin>644</xmin><ymin>922</ymin><xmax>835</xmax><ymax>1003</ymax></bndbox><confidence>0.9563</confidence></object><object><name>ayat_line</name><pose>Unspecified</pose><truncated>0</truncated><difficult>0</difficult><bndbox><xmin>88</xmin><ymin>1154</ymin><xmax>238</xmax><ymax>1234</ymax></bndbox><confidence>0.9502</confidence></object><object><name>ayat_line</name><pose>Unspecified</pose><truncated>0</truncated><difficult>0</difficult><bndbox><xmin>620</xmin><ymin>539</ymin><xmax>835</xmax><ymax>616</ymax></bndbox><confidence>0.9486</confidence></object><object><name>ayat_line</name><pose>Unspecified</pose><truncated>0</truncated><difficult>0</difficult><bndbox><xmin>88</xmin><ymin>1003</ymin><xmax>198</xmax><ymax>1077</ymax></bndbox><confidence>0.9471</confidence></object><object><name>ayah_marker</name><pose>Unspecified</pose><truncated>0</truncated><difficult>0</difficult><bndbox><xmin>94</xmin><ymin>1249</ymin><xmax>140</xmax><ymax>1300</ymax></bndbox><confidence>0.9228</confidence></object><object><name>ayah_marker</name><pose>Unspecified</pose><truncated>0</truncated><difficult>0</difficult><bndbox><xmin>238</xmin><ymin>1173</ymin><xmax>280</xmax><ymax>1223</ymax></bndbox><confidence>0.9183</confidence></object><object><name>ayah_marker</name><pose>Unspecified</pose><truncated>0</truncated><difficult>0</difficult><bndbox><xmin>97</xmin><ymin>711</ymin><xmax>141</xmax><ymax>760</ymax></bndbox><confidence>0.9183</confidence></object><object><name>ayah_marker</name><pose>Unspecified</pose><truncated>0</truncated><difficult>0</difficult><bndbox><xmin>644</xmin><ymin>560</ymin><xmax>688</xmax><ymax>610</ymax></bndbox><confidence>0.9176</confidence></object><object><name>ayah_marker</name><pose>Unspecified</pose><truncated>0</truncated><difficult>0</difficult><bndbox><xmin>644</xmin><ymin>942</ymin><xmax>687</xmax><ymax>992</ymax></bndbox><confidence>0.9168</confidence></object><object><name>ayah_marker</name><pose>Unspecified</pose><truncated>0</truncated><difficult>0</difficult><bndbox><xmin>199</xmin><ymin>1019</ymin><xmax>243</xmax><ymax>1069</ymax></bndbox><confidence>0.9141</confidence></object><object><name>ayah_marker</name><pose>Unspecified</pose><truncated>0</truncated><difficult>0</difficult><bndbox><xmin>631</xmin><ymin>406</ymin><xmax>676</xmax><ymax>455</ymax></bndbox><confidence>0.9132</confidence></object></annotation>