<?xml version='1.0' encoding='utf-8'?>
<annotation verified="yes">
	<folder>training_images</folder>
	<filename>tikrar-tajwid-terjemah_page_079.webp</filename>
	<path>/Users/syaamil/development/Quran-Bounding/MODEL TRAINER/datasets/images/test_validation/tikrar-tajwid-terjemah_page_079.webp</path>
	<source>
		<database>Unknown</database>
	</source>
	<size>
		<width>1000</width>
		<height>1579</height>
		<depth>3</depth>
	</size>
	<segmented>0</segmented>
	<object>
		<name>ayat_line</name>
		<pose>Unspecified</pose>
		<truncated>0</truncated>
		<difficult>0</difficult>
		<bndbox>
			<xmin>34</xmin>
			<ymin>77</ymin>
			<xmax>949</xmax>
			<ymax>1029</ymax>
		</bndbox>
	</object>
	<object>
		<name>ayat_line</name>
		<pose>Unspecified</pose>
		<truncated>0</truncated>
		<difficult>0</difficult>
		<bndbox>
			<xmin>860</xmin>
			<ymin>1029</ymin>
			<xmax>949</xmax>
			<ymax>1126</ymax>
		</bndbox>
	</object>
	<object>
		<name>ayat_line</name>
		<pose>Unspecified</pose>
		<truncated>0</truncated>
		<difficult>0</difficult>
		<bndbox>
			<xmin>34</xmin>
			<ymin>1029</ymin>
			<xmax>860</xmax>
			<ymax>1126</ymax>
		</bndbox>
	</object>
	<object>
		<name>ayat_line</name>
		<pose>Unspecified</pose>
		<truncated>0</truncated>
		<difficult>0</difficult>
		<bndbox>
			<xmin>34</xmin>
			<ymin>1126</ymin>
			<xmax>949</xmax>
			<ymax>1314</ymax>
		</bndbox>
	</object>
	<object>
		<name>ayat_line</name>
		<pose>Unspecified</pose>
		<truncated>0</truncated>
		<difficult>0</difficult>
		<bndbox>
			<xmin>34</xmin>
			<ymin>1314</ymin>
			<xmax>949</xmax>
			<ymax>1525</ymax>
		</bndbox>
	</object>
	<object>
		<name>ayah_marker</name>
		<pose>Unspecified</pose>
		<truncated>0</truncated>
		<difficult>0</difficult>
		<bndbox>
			<xmin>57</xmin>
			<ymin>1225</ymin>
			<xmax>123</xmax>
			<ymax>1299</ymax>
		</bndbox>
	</object>
	<object>
		<name>ayah_marker</name>
		<pose>Unspecified</pose>
		<truncated>0</truncated>
		<difficult>0</difficult>
		<bndbox>
			<xmin>57</xmin>
			<ymin>1415</ymin>
			<xmax>123</xmax>
			<ymax>1491</ymax>
		</bndbox>
	</object>
	<object>
		<name>ayah_marker</name>
		<pose>Unspecified</pose>
		<truncated>0</truncated>
		<difficult>0</difficult>
		<bndbox>
			<xmin>864</xmin>
			<ymin>1035</ymin>
			<xmax>930</xmax>
			<ymax>1110</ymax>
		</bndbox>
	</object>
</annotation>
