<?xml version='1.0' encoding='utf-8'?>
<annotation verified="yes">
	<folder>training_images</folder>
	<filename>haji-umrah_page_294.webp</filename>
	<path>/Users/syaamil/development/Quran-Bounding/MODEL TRAINER/datasets/training_images/haji-umrah_page_294.webp</path>
	<source>
		<database>Unknown</database>
	</source>
	<size>
		<width>1000</width>
		<height>1586</height>
		<depth>3</depth>
	</size>
	<segmented>0</segmented>
	<object>
		<name>ayat_line</name>
		<pose>Unspecified</pose>
		<truncated>0</truncated>
		<difficult>0</difficult>
		<bndbox>
			<xmin>49</xmin>
			<ymin>90</ymin>
			<xmax>991</xmax>
			<ymax>188</ymax>
		</bndbox>
	</object>
	<object>
		<name>ayat_line</name>
		<pose>Unspecified</pose>
		<truncated>0</truncated>
		<difficult>0</difficult>
		<bndbox>
			<xmin>428</xmin>
			<ymin>188</ymin>
			<xmax>991</xmax>
			<ymax>286</ymax>
		</bndbox>
	</object>
	<object>
		<name>ayat_line</name>
		<pose>Unspecified</pose>
		<truncated>0</truncated>
		<difficult>0</difficult>
		<bndbox>
			<xmin>141</xmin>
			<ymin>286</ymin>
			<xmax>991</xmax>
			<ymax>384</ymax>
		</bndbox>
	</object>
	<object>
		<name>ayat_line</name>
		<pose>Unspecified</pose>
		<truncated>0</truncated>
		<difficult>0</difficult>
		<bndbox>
			<xmin>49</xmin>
			<ymin>188</ymin>
			<xmax>428</xmax>
			<ymax>286</ymax>
		</bndbox>
	</object>
	<object>
		<name>ayat_line</name>
		<pose>Unspecified</pose>
		<truncated>0</truncated>
		<difficult>0</difficult>
		<bndbox>
			<xmin>49</xmin>
			<ymin>286</ymin>
			<xmax>141</xmax>
			<ymax>384</ymax>
		</bndbox>
	</object>
	<object>
		<name>ayat_line</name>
		<pose>Unspecified</pose>
		<truncated>0</truncated>
		<difficult>0</difficult>
		<bndbox>
			<xmin>49</xmin>
			<ymin>384</ymin>
			<xmax>991</xmax>
			<ymax>481</ymax>
		</bndbox>
	</object>
	<object>
		<name>ayat_line</name>
		<pose>Unspecified</pose>
		<truncated>0</truncated>
		<difficult>0</difficult>
		<bndbox>
			<xmin>917</xmin>
			<ymin>481</ymin>
			<xmax>991</xmax>
			<ymax>579</ymax>
		</bndbox>
	</object>
	<object>
		<name>ayat_line</name>
		<pose>Unspecified</pose>
		<truncated>0</truncated>
		<difficult>0</difficult>
		<bndbox>
			<xmin>260</xmin>
			<ymin>481</ymin>
			<xmax>917</xmax>
			<ymax>579</ymax>
		</bndbox>
	</object>
	<object>
		<name>ayat_line</name>
		<pose>Unspecified</pose>
		<truncated>0</truncated>
		<difficult>0</difficult>
		<bndbox>
			<xmin>49</xmin>
			<ymin>579</ymin>
			<xmax>991</xmax>
			<ymax>677</ymax>
		</bndbox>
	</object>
	<object>
		<name>ayat_line</name>
		<pose>Unspecified</pose>
		<truncated>0</truncated>
		<difficult>0</difficult>
		<bndbox>
			<xmin>49</xmin>
			<ymin>481</ymin>
			<xmax>260</xmax>
			<ymax>579</ymax>
		</bndbox>
	</object>
	<object>
		<name>ayat_line</name>
		<pose>Unspecified</pose>
		<truncated>0</truncated>
		<difficult>0</difficult>
		<bndbox>
			<xmin>49</xmin>
			<ymin>677</ymin>
			<xmax>991</xmax>
			<ymax>773</ymax>
		</bndbox>
	</object>
	<object>
		<name>ayat_line</name>
		<pose>Unspecified</pose>
		<truncated>0</truncated>
		<difficult>0</difficult>
		<bndbox>
			<xmin>412</xmin>
			<ymin>773</ymin>
			<xmax>991</xmax>
			<ymax>871</ymax>
		</bndbox>
	</object>
	<object>
		<name>ayat_line</name>
		<pose>Unspecified</pose>
		<truncated>0</truncated>
		<difficult>0</difficult>
		<bndbox>
			<xmin>443</xmin>
			<ymin>871</ymin>
			<xmax>991</xmax>
			<ymax>969</ymax>
		</bndbox>
	</object>
	<object>
		<name>ayat_line</name>
		<pose>Unspecified</pose>
		<truncated>0</truncated>
		<difficult>0</difficult>
		<bndbox>
			<xmin>49</xmin>
			<ymin>773</ymin>
			<xmax>412</xmax>
			<ymax>871</ymax>
		</bndbox>
	</object>
	<object>
		<name>ayat_line</name>
		<pose>Unspecified</pose>
		<truncated>0</truncated>
		<difficult>0</difficult>
		<bndbox>
			<xmin>420</xmin>
			<ymin>969</ymin>
			<xmax>991</xmax>
			<ymax>1067</ymax>
		</bndbox>
	</object>
	<object>
		<name>ayat_line</name>
		<pose>Unspecified</pose>
		<truncated>0</truncated>
		<difficult>0</difficult>
		<bndbox>
			<xmin>49</xmin>
			<ymin>871</ymin>
			<xmax>443</xmax>
			<ymax>969</ymax>
		</bndbox>
	</object>
	<object>
		<name>ayat_line</name>
		<pose>Unspecified</pose>
		<truncated>0</truncated>
		<difficult>0</difficult>
		<bndbox>
			<xmin>49</xmin>
			<ymin>1067</ymin>
			<xmax>991</xmax>
			<ymax>1165</ymax>
		</bndbox>
	</object>
	<object>
		<name>ayat_line</name>
		<pose>Unspecified</pose>
		<truncated>0</truncated>
		<difficult>0</difficult>
		<bndbox>
			<xmin>49</xmin>
			<ymin>969</ymin>
			<xmax>420</xmax>
			<ymax>1067</ymax>
		</bndbox>
	</object>
	<object>
		<name>ayat_line</name>
		<pose>Unspecified</pose>
		<truncated>0</truncated>
		<difficult>0</difficult>
		<bndbox>
			<xmin>49</xmin>
			<ymin>1165</ymin>
			<xmax>991</xmax>
			<ymax>1359</ymax>
		</bndbox>
	</object>
	<object>
		<name>ayat_line</name>
		<pose>Unspecified</pose>
		<truncated>0</truncated>
		<difficult>0</difficult>
		<bndbox>
			<xmin>49</xmin>
			<ymin>1359</ymin>
			<xmax>991</xmax>
			<ymax>1555</ymax>
		</bndbox>
	</object>
	<object>
		<name>ayah_marker</name>
		<pose>Unspecified</pose>
		<truncated>0</truncated>
		<difficult>0</difficult>
		<bndbox>
			<xmin>143</xmin>
			<ymin>310</ymin>
			<xmax>194</xmax>
			<ymax>370</ymax>
		</bndbox>
	</object>
	<object>
		<name>ayah_marker</name>
		<pose>Unspecified</pose>
		<truncated>0</truncated>
		<difficult>0</difficult>
		<bndbox>
			<xmin>444</xmin>
			<ymin>900</ymin>
			<xmax>498</xmax>
			<ymax>960</ymax>
		</bndbox>
	</object>
	<object>
		<name>ayah_marker</name>
		<pose>Unspecified</pose>
		<truncated>0</truncated>
		<difficult>0</difficult>
		<bndbox>
			<xmin>429</xmin>
			<ymin>212</ymin>
			<xmax>482</xmax>
			<ymax>271</ymax>
		</bndbox>
	</object>
	<object>
		<name>ayah_marker</name>
		<pose>Unspecified</pose>
		<truncated>0</truncated>
		<difficult>0</difficult>
		<bndbox>
			<xmin>71</xmin>
			<ymin>1284</ymin>
			<xmax>122</xmax>
			<ymax>1344</ymax>
		</bndbox>
	</object>
	<object>
		<name>ayah_marker</name>
		<pose>Unspecified</pose>
		<truncated>0</truncated>
		<difficult>0</difficult>
		<bndbox>
			<xmin>70</xmin>
			<ymin>1092</ymin>
			<xmax>124</xmax>
			<ymax>1150</ymax>
		</bndbox>
	</object>
	<object>
		<name>ayah_marker</name>
		<pose>Unspecified</pose>
		<truncated>0</truncated>
		<difficult>0</difficult>
		<bndbox>
			<xmin>264</xmin>
			<ymin>505</ymin>
			<xmax>315</xmax>
			<ymax>564</ymax>
		</bndbox>
	</object>
	<object>
		<name>ayah_marker</name>
		<pose>Unspecified</pose>
		<truncated>0</truncated>
		<difficult>0</difficult>
		<bndbox>
			<xmin>420</xmin>
			<ymin>997</ymin>
			<xmax>473</xmax>
			<ymax>1056</ymax>
		</bndbox>
	</object>
	<object>
		<name>ayah_marker</name>
		<pose>Unspecified</pose>
		<truncated>0</truncated>
		<difficult>0</difficult>
		<bndbox>
			<xmin>64</xmin>
			<ymin>1475</ymin>
			<xmax>115</xmax>
			<ymax>1534</ymax>
		</bndbox>
	</object>
	<object>
		<name>ayah_marker</name>
		<pose>Unspecified</pose>
		<truncated>0</truncated>
		<difficult>0</difficult>
		<bndbox>
			<xmin>919</xmin>
			<ymin>511</ymin>
			<xmax>972</xmax>
			<ymax>570</ymax>
		</bndbox>
	</object>
	<object>
		<name>ayah_marker</name>
		<pose>Unspecified</pose>
		<truncated>0</truncated>
		<difficult>0</difficult>
		<bndbox>
			<xmin>72</xmin>
			<ymin>605</ymin>
			<xmax>126</xmax>
			<ymax>664</ymax>
		</bndbox>
	</object>
	<object>
		<name>ayah_marker</name>
		<pose>Unspecified</pose>
		<truncated>0</truncated>
		<difficult>0</difficult>
		<bndbox>
			<xmin>414</xmin>
			<ymin>802</ymin>
			<xmax>467</xmax>
			<ymax>862</ymax>
		</bndbox>
	</object>
</annotation>
