<?xml version='1.0' encoding='utf-8'?>
<annotation verified="no"><folder>model-v2-mina</folder><filename>mina_page_215.webp</filename><path>/Users/syaamil/development/Quran-Bounding/quran-bounding-project/experiments/model-v2-mina/mina_page_215.webp</path><source><database>Unknown</database></source><size><width>1000</width><height>1452</height><depth>3</depth></size><segmented>0</segmented><object><name>ayat_line</name><pose>Unspecified</pose><truncated>0</truncated><difficult>0</difficult><bndbox><xmin>88</xmin><ymin>1072</ymin><xmax>834</xmax><ymax>1316</ymax></bndbox><confidence>0.9755</confidence></object><object><name>ayat_line</name><pose>Unspecified</pose><truncated>0</truncated><difficult>0</difficult><bndbox><xmin>87</xmin><ymin>997</ymin><xmax>626</xmax><ymax>1072</ymax></bndbox><confidence>0.9727</confidence></object><object><name>ayat_line</name><pose>Unspecified</pose><truncated>0</truncated><difficult>0</difficult><bndbox><xmin>88</xmin><ymin>915</ymin><xmax>833</xmax><ymax>996</ymax></bndbox><confidence>0.9727</confidence></object><object><name>ayat_line</name><pose>Unspecified</pose><truncated>0</truncated><difficult>0</difficult><bndbox><xmin>89</xmin><ymin>303</ymin><xmax>626</xmax><ymax>380</ymax></bndbox><confidence>0.9722</confidence></object><object><name>ayat_line</name><pose>Unspecified</pose><truncated>0</truncated><difficult>0</difficult><bndbox><xmin>88</xmin><ymin>841</ymin><xmax>625</xmax><ymax>915</ymax></bndbox><confidence>0.9706</confidence></object><object><name>ayat_line</name><pose>Unspecified</pose><truncated>0</truncated><difficult>0</difficult><bndbox><xmin>88</xmin><ymin>766</ymin><xmax>833</xmax><ymax>841</ymax></bndbox><confidence>0.9691</confidence></object><object><name>ayat_line</name><pose>Unspecified</pose><truncated>0</truncated><difficult>0</difficult><bndbox><xmin>272</xmin><ymin>380</ymin><xmax>834</xmax><ymax>458</ymax></bndbox><confidence>0.9690</confidence></object><object><name>ayat_line</name><pose>Unspecified</pose><truncated>0</truncated><difficult>0</difficult><bndbox><xmin>88</xmin><ymin>693</ymin><xmax>638</xmax><ymax>766</ymax></bndbox><confidence>0.9687</confidence></object><object><name>ayat_line</name><pose>Unspecified</pose><truncated>0</truncated><difficult>0</difficult><bndbox><xmin>626</xmin><ymin>303</ymin><xmax>835</xmax><ymax>380</ymax></bndbox><confidence>0.9657</confidence></object><object><name>ayat_line</name><pose>Unspecified</pose><truncated>0</truncated><difficult>0</difficult><bndbox><xmin>88</xmin><ymin>608</ymin><xmax>784</xmax><ymax>693</ymax></bndbox><confidence>0.9653</confidence></object><object><name>ayat_line</name><pose>Unspecified</pose><truncated>0</truncated><difficult>0</difficult><bndbox><xmin>570</xmin><ymin>457</ymin><xmax>835</xmax><ymax>533</ymax></bndbox><confidence>0.9644</confidence></object><object><name>ayat_line</name><pose>Unspecified</pose><truncated>0</truncated><difficult>0</difficult><bndbox><xmin>625</xmin><ymin>841</ymin><xmax>835</xmax><ymax>915</ymax></bndbox><confidence>0.9639</confidence></object><object><name>ayat_line</name><pose>Unspecified</pose><truncated>0</truncated><difficult>0</difficult><bndbox><xmin>87</xmin><ymin>380</ymin><xmax>272</xmax><ymax>458</ymax></bndbox><confidence>0.9617</confidence></object><object><name>ayat_line</name><pose>Unspecified</pose><truncated>0</truncated><difficult>0</difficult><bndbox><xmin>626</xmin><ymin>997</ymin><xmax>835</xmax><ymax>1072</ymax></bndbox><confidence>0.9615</confidence></object><object><name>ayat_line</name><pose>Unspecified</pose><truncated>0</truncated><difficult>0</difficult><bndbox><xmin>87</xmin><ymin>457</ymin><xmax>570</xmax><ymax>532</ymax></bndbox><confidence>0.9594</confidence></object><object><name>ayat_line</name><pose>Unspecified</pose><truncated>0</truncated><difficult>0</difficult><bndbox><xmin>87</xmin><ymin>532</ymin><xmax>834</xmax><ymax>608</ymax></bndbox><confidence>0.9565</confidence></object><object><name>ayat_line</name><pose>Unspecified</pose><truncated>0</truncated><difficult>0</difficult><bndbox><xmin>637</xmin><ymin>693</ymin><xmax>835</xmax><ymax>766</ymax></bndbox><confidence>0.9548</confidence></object><object><name>ayat_line</name><pose>Unspecified</pose><truncated>0</truncated><difficult>0</difficult><bndbox><xmin>785</xmin><ymin>608</ymin><xmax>835</xmax><ymax>692</ymax></bndbox><confidence>0.9430</confidence></object><object><name>ayah_marker</name><pose>Unspecified</pose><truncated>0</truncated><difficult>0</difficult><bndbox><xmin>572</xmin><ymin>478</ymin><xmax>614</xmax><ymax>525</ymax></bndbox><confidence>0.9251</confidence></object><object><name>ayah_marker</name><pose>Unspecified</pose><truncated>0</truncated><difficult>0</difficult><bndbox><xmin>625</xmin><ymin>863</ymin><xmax>666</xmax><ymax>909</ymax></bndbox><confidence>0.9237</confidence></object><object><name>ayah_marker</name><pose>Unspecified</pose><truncated>0</truncated><difficult>0</difficult><bndbox><xmin>638</xmin><ymin>710</ymin><xmax>680</xmax><ymax>756</ymax></bndbox><confidence>0.9152</confidence></object><object><name>ayah_marker</name><pose>Unspecified</pose><truncated>0</truncated><difficult>0</difficult><bndbox><xmin>626</xmin><ymin>1017</ymin><xmax>669</xmax><ymax>1064</ymax></bndbox><confidence>0.9150</confidence></object><object><name>ayah_marker</name><pose>Unspecified</pose><truncated>0</truncated><difficult>0</difficult><bndbox><xmin>627</xmin><ymin>323</ymin><xmax>669</xmax><ymax>370</ymax></bndbox><confidence>0.9138</confidence></object><object><name>ayah_marker</name><pose>Unspecified</pose><truncated>0</truncated><difficult>0</difficult><bndbox><xmin>273</xmin><ymin>401</ymin><xmax>315</xmax><ymax>447</ymax></bndbox><confidence>0.9131</confidence></object><object><name>ayah_marker</name><pose>Unspecified</pose><truncated>0</truncated><difficult>0</difficult><bndbox><xmin>95</xmin><ymin>1248</ymin><xmax>138</xmax><ymax>1295</ymax></bndbox><confidence>0.9125</confidence></object><object><name>ayah_marker</name><pose>Unspecified</pose><truncated>0</truncated><difficult>0</difficult><bndbox><xmin>786</xmin><ymin>633</ymin><xmax>828</xmax><ymax>680</ymax></bndbox><confidence>0.9075</confidence></object><object><name>ayat_line</name><pose>Unspecified</pose><truncated>0</truncated><difficult>0</difficult><bndbox><xmin>88</xmin><ymin>139</ymin><xmax>833</xmax><ymax>303</ymax></bndbox><confidence>0.8413</confidence></object></annotation>