<?xml version='1.0' encoding='utf-8'?>
<annotation verified="no"><folder>model-v2-mina</folder><filename>mina_page_514.webp</filename><path>/Users/syaamil/development/Quran-Bounding/quran-bounding-project/experiments/model-v2-mina/mina_page_514.webp</path><source><database>Unknown</database></source><size><width>1000</width><height>1452</height><depth>3</depth></size><segmented>0</segmented><object><name>ayat_line</name><pose>Unspecified</pose><truncated>0</truncated><difficult>0</difficult><bndbox><xmin>161</xmin><ymin>302</ymin><xmax>907</xmax><ymax>616</ymax></bndbox><confidence>0.9845</confidence></object><object><name>ayat_line</name><pose>Unspecified</pose><truncated>0</truncated><difficult>0</difficult><bndbox><xmin>161</xmin><ymin>921</ymin><xmax>908</xmax><ymax>1154</ymax></bndbox><confidence>0.9798</confidence></object><object><name>ayat_line</name><pose>Unspecified</pose><truncated>0</truncated><difficult>0</difficult><bndbox><xmin>161</xmin><ymin>689</ymin><xmax>908</xmax><ymax>921</ymax></bndbox><confidence>0.9753</confidence></object><object><name>ayat_line</name><pose>Unspecified</pose><truncated>0</truncated><difficult>0</difficult><bndbox><xmin>161</xmin><ymin>1154</ymin><xmax>699</xmax><ymax>1233</ymax></bndbox><confidence>0.9680</confidence></object><object><name>ayat_line</name><pose>Unspecified</pose><truncated>0</truncated><difficult>0</difficult><bndbox><xmin>699</xmin><ymin>1154</ymin><xmax>909</xmax><ymax>1233</ymax></bndbox><confidence>0.9649</confidence></object><object><name>ayat_line</name><pose>Unspecified</pose><truncated>0</truncated><difficult>0</difficult><bndbox><xmin>161</xmin><ymin>1233</ymin><xmax>908</xmax><ymax>1317</ymax></bndbox><confidence>0.9607</confidence></object><object><name>ayat_line</name><pose>Unspecified</pose><truncated>0</truncated><difficult>0</difficult><bndbox><xmin>161</xmin><ymin>615</ymin><xmax>458</xmax><ymax>688</ymax></bndbox><confidence>0.9503</confidence></object><object><name>ayat_line</name><pose>Unspecified</pose><truncated>0</truncated><difficult>0</difficult><bndbox><xmin>459</xmin><ymin>615</ymin><xmax>908</xmax><ymax>688</ymax></bndbox><confidence>0.9476</confidence></object><object><name>ayat_line</name><pose>Unspecified</pose><truncated>0</truncated><difficult>0</difficult><bndbox><xmin>162</xmin><ymin>140</ymin><xmax>909</xmax><ymax>303</ymax></bndbox><confidence>0.9426</confidence></object><object><name>ayah_marker</name><pose>Unspecified</pose><truncated>0</truncated><difficult>0</difficult><bndbox><xmin>167</xmin><ymin>243</ymin><xmax>213</xmax><ymax>293</ymax></bndbox><confidence>0.9231</confidence></object><object><name>ayah_marker</name><pose>Unspecified</pose><truncated>0</truncated><difficult>0</difficult><bndbox><xmin>166</xmin><ymin>1244</ymin><xmax>212</xmax><ymax>1294</ymax></bndbox><confidence>0.9190</confidence></object><object><name>ayah_marker</name><pose>Unspecified</pose><truncated>0</truncated><difficult>0</difficult><bndbox><xmin>459</xmin><ymin>629</ymin><xmax>502</xmax><ymax>678</ymax></bndbox><confidence>0.9163</confidence></object><object><name>ayah_marker</name><pose>Unspecified</pose><truncated>0</truncated><difficult>0</difficult><bndbox><xmin>700</xmin><ymin>1169</ymin><xmax>745</xmax><ymax>1219</ymax></bndbox><confidence>0.9162</confidence></object><object><name>ayah_marker</name><pose>Unspecified</pose><truncated>0</truncated><difficult>0</difficult><bndbox><xmin>168</xmin><ymin>859</ymin><xmax>213</xmax><ymax>908</ymax></bndbox><confidence>0.9151</confidence></object></annotation>