<?xml version='1.0' encoding='utf-8'?>
<annotation verified="no"><folder>images</folder><filename>quba-page_484.jpg</filename><path>/Users/syaamil/development/Quran-Bounding/quran-bounding-project/experiments/model-v1/images/quba-page_484.jpg</path><source><database>Unknown</database></source><size><width>814</width><height>1169</height><depth>3</depth></size><segmented>0</segmented><object><name>ayat_line</name><pose>Unspecified</pose><truncated>0</truncated><difficult>0</difficult><bndbox><xmin>69</xmin><ymin>347</ymin><xmax>739</xmax><ymax>557</ymax></bndbox><confidence>0.9845</confidence></object><object><name>ayat_line</name><pose>Unspecified</pose><truncated>0</truncated><difficult>0</difficult><bndbox><xmin>68</xmin><ymin>836</ymin><xmax>738</xmax><ymax>1119</ymax></bndbox><confidence>0.9803</confidence></object><object><name>ayat_line</name><pose>Unspecified</pose><truncated>0</truncated><difficult>0</difficult><bndbox><xmin>68</xmin><ymin>65</ymin><xmax>739</xmax><ymax>206</ymax></bndbox><confidence>0.9726</confidence></object><object><name>ayat_line</name><pose>Unspecified</pose><truncated>0</truncated><difficult>0</difficult><bndbox><xmin>69</xmin><ymin>627</ymin><xmax>739</xmax><ymax>766</ymax></bndbox><confidence>0.9689</confidence></object><object><name>ayat_line</name><pose>Unspecified</pose><truncated>0</truncated><difficult>0</difficult><bndbox><xmin>196</xmin><ymin>556</ymin><xmax>741</xmax><ymax>627</ymax></bndbox><confidence>0.9672</confidence></object><object><name>ayat_line</name><pose>Unspecified</pose><truncated>0</truncated><difficult>0</difficult><bndbox><xmin>68</xmin><ymin>206</ymin><xmax>492</xmax><ymax>275</ymax></bndbox><confidence>0.9668</confidence></object><object><name>ayat_line</name><pose>Unspecified</pose><truncated>0</truncated><difficult>0</difficult><bndbox><xmin>492</xmin><ymin>205</ymin><xmax>739</xmax><ymax>275</ymax></bndbox><confidence>0.9650</confidence></object><object><name>ayat_line</name><pose>Unspecified</pose><truncated>0</truncated><difficult>0</difficult><bndbox><xmin>68</xmin><ymin>766</ymin><xmax>153</xmax><ymax>836</ymax></bndbox><confidence>0.9643</confidence></object><object><name>ayat_line</name><pose>Unspecified</pose><truncated>0</truncated><difficult>0</difficult><bndbox><xmin>157</xmin><ymin>275</ymin><xmax>740</xmax><ymax>346</ymax></bndbox><confidence>0.9636</confidence></object><object><name>ayat_line</name><pose>Unspecified</pose><truncated>0</truncated><difficult>0</difficult><bndbox><xmin>154</xmin><ymin>766</ymin><xmax>741</xmax><ymax>836</ymax></bndbox><confidence>0.9618</confidence></object><object><name>ayat_line</name><pose>Unspecified</pose><truncated>0</truncated><difficult>0</difficult><bndbox><xmin>69</xmin><ymin>557</ymin><xmax>196</xmax><ymax>626</ymax></bndbox><confidence>0.9548</confidence></object><object><name>ayat_line</name><pose>Unspecified</pose><truncated>0</truncated><difficult>0</difficult><bndbox><xmin>67</xmin><ymin>275</ymin><xmax>157</xmax><ymax>347</ymax></bndbox><confidence>0.9485</confidence></object><object><name>ayah_marker</name><pose>Unspecified</pose><truncated>0</truncated><difficult>0</difficult><bndbox><xmin>153</xmin><ymin>778</ymin><xmax>193</xmax><ymax>823</ymax></bndbox><confidence>0.9267</confidence></object><object><name>ayah_marker</name><pose>Unspecified</pose><truncated>0</truncated><difficult>0</difficult><bndbox><xmin>196</xmin><ymin>572</ymin><xmax>236</xmax><ymax>616</ymax></bndbox><confidence>0.9238</confidence></object><object><name>ayah_marker</name><pose>Unspecified</pose><truncated>0</truncated><difficult>0</difficult><bndbox><xmin>493</xmin><ymin>224</ymin><xmax>532</xmax><ymax>269</ymax></bndbox><confidence>0.9201</confidence></object><object><name>ayah_marker</name><pose>Unspecified</pose><truncated>0</truncated><difficult>0</difficult><bndbox><xmin>79</xmin><ymin>1058</ymin><xmax>119</xmax><ymax>1102</ymax></bndbox><confidence>0.9193</confidence></object><object><name>ayah_marker</name><pose>Unspecified</pose><truncated>0</truncated><difficult>0</difficult><bndbox><xmin>176</xmin><ymin>294</ymin><xmax>215</xmax><ymax>339</ymax></bndbox><confidence>0.9174</confidence></object></annotation>