<?xml version='1.0' encoding='utf-8'?>
<annotation verified="no"><folder>images</folder><filename>quba-page_596.jpg</filename><path>/Users/syaamil/development/Quran-Bounding/quran-bounding-project/experiments/model-v1/images/quba-page_596.jpg</path><source><database>Unknown</database></source><size><width>814</width><height>1169</height><depth>3</depth></size><segmented>0</segmented><object><name>ayat_line</name><pose>Unspecified</pose><truncated>0</truncated><difficult>0</difficult><bndbox><xmin>67</xmin><ymin>907</ymin><xmax>397</xmax><ymax>976</ymax></bndbox><confidence>0.9752</confidence></object><object><name>ayat_line</name><pose>Unspecified</pose><truncated>0</truncated><difficult>0</difficult><bndbox><xmin>68</xmin><ymin>417</ymin><xmax>363</xmax><ymax>487</ymax></bndbox><confidence>0.9712</confidence></object><object><name>ayat_line</name><pose>Unspecified</pose><truncated>0</truncated><difficult>0</difficult><bndbox><xmin>397</xmin><ymin>907</ymin><xmax>740</xmax><ymax>976</ymax></bndbox><confidence>0.9698</confidence></object><object><name>ayat_line</name><pose>Unspecified</pose><truncated>0</truncated><difficult>0</difficult><bndbox><xmin>503</xmin><ymin>976</ymin><xmax>740</xmax><ymax>1046</ymax></bndbox><confidence>0.9686</confidence></object><object><name>ayat_line</name><pose>Unspecified</pose><truncated>0</truncated><difficult>0</difficult><bndbox><xmin>301</xmin><ymin>977</ymin><xmax>502</xmax><ymax>1046</ymax></bndbox><confidence>0.9681</confidence></object><object><name>ayat_line</name><pose>Unspecified</pose><truncated>0</truncated><difficult>0</difficult><bndbox><xmin>68</xmin><ymin>556</ymin><xmax>315</xmax><ymax>627</ymax></bndbox><confidence>0.9676</confidence></object><object><name>ayat_line</name><pose>Unspecified</pose><truncated>0</truncated><difficult>0</difficult><bndbox><xmin>316</xmin><ymin>556</ymin><xmax>608</xmax><ymax>627</ymax></bndbox><confidence>0.9676</confidence></object><object><name>ayat_line</name><pose>Unspecified</pose><truncated>0</truncated><difficult>0</difficult><bndbox><xmin>68</xmin><ymin>976</ymin><xmax>300</xmax><ymax>1046</ymax></bndbox><confidence>0.9660</confidence></object><object><name>ayat_line</name><pose>Unspecified</pose><truncated>0</truncated><difficult>0</difficult><bndbox><xmin>363</xmin><ymin>417</ymin><xmax>579</xmax><ymax>487</ymax></bndbox><confidence>0.9657</confidence></object><object><name>ayat_line</name><pose>Unspecified</pose><truncated>0</truncated><difficult>0</difficult><bndbox><xmin>68</xmin><ymin>487</ymin><xmax>369</xmax><ymax>556</ymax></bndbox><confidence>0.9648</confidence></object><object><name>ayat_line</name><pose>Unspecified</pose><truncated>0</truncated><difficult>0</difficult><bndbox><xmin>68</xmin><ymin>136</ymin><xmax>358</xmax><ymax>206</ymax></bndbox><confidence>0.9647</confidence></object><object><name>ayat_line</name><pose>Unspecified</pose><truncated>0</truncated><difficult>0</difficult><bndbox><xmin>214</xmin><ymin>65</ymin><xmax>437</xmax><ymax>136</ymax></bndbox><confidence>0.9641</confidence></object><object><name>ayat_line</name><pose>Unspecified</pose><truncated>0</truncated><difficult>0</difficult><bndbox><xmin>386</xmin><ymin>627</ymin><xmax>690</xmax><ymax>697</ymax></bndbox><confidence>0.9639</confidence></object><object><name>ayat_line</name><pose>Unspecified</pose><truncated>0</truncated><difficult>0</difficult><bndbox><xmin>68</xmin><ymin>627</ymin><xmax>384</xmax><ymax>697</ymax></bndbox><confidence>0.9637</confidence></object><object><name>ayat_line</name><pose>Unspecified</pose><truncated>0</truncated><difficult>0</difficult><bndbox><xmin>520</xmin><ymin>1046</ymin><xmax>740</xmax><ymax>1118</ymax></bndbox><confidence>0.9634</confidence></object><object><name>ayat_line</name><pose>Unspecified</pose><truncated>0</truncated><difficult>0</difficult><bndbox><xmin>359</xmin><ymin>136</ymin><xmax>617</xmax><ymax>206</ymax></bndbox><confidence>0.9631</confidence></object><object><name>ayat_line</name><pose>Unspecified</pose><truncated>0</truncated><difficult>0</difficult><bndbox><xmin>579</xmin><ymin>417</ymin><xmax>740</xmax><ymax>487</ymax></bndbox><confidence>0.9631</confidence></object><object><name>ayat_line</name><pose>Unspecified</pose><truncated>0</truncated><difficult>0</difficult><bndbox><xmin>68</xmin><ymin>206</ymin><xmax>282</xmax><ymax>275</ymax></bndbox><confidence>0.9625</confidence></object><object><name>ayat_line</name><pose>Unspecified</pose><truncated>0</truncated><difficult>0</difficult><bndbox><xmin>369</xmin><ymin>487</ymin><xmax>740</xmax><ymax>556</ymax></bndbox><confidence>0.9625</confidence></object><object><name>ayat_line</name><pose>Unspecified</pose><truncated>0</truncated><difficult>0</difficult><bndbox><xmin>69</xmin><ymin>349</ymin><xmax>739</xmax><ymax>417</ymax></bndbox><confidence>0.9624</confidence></object><object><name>ayat_line</name><pose>Unspecified</pose><truncated>0</truncated><difficult>0</difficult><bndbox><xmin>68</xmin><ymin>697</ymin><xmax>420</xmax><ymax>765</ymax></bndbox><confidence>0.9619</confidence></object><object><name>ayat_line</name><pose>Unspecified</pose><truncated>0</truncated><difficult>0</difficult><bndbox><xmin>420</xmin><ymin>697</ymin><xmax>739</xmax><ymax>765</ymax></bndbox><confidence>0.9619</confidence></object><object><name>ayat_line</name><pose>Unspecified</pose><truncated>0</truncated><difficult>0</difficult><bndbox><xmin>67</xmin><ymin>837</ymin><xmax>739</xmax><ymax>907</ymax></bndbox><confidence>0.9615</confidence></object><object><name>ayat_line</name><pose>Unspecified</pose><truncated>0</truncated><difficult>0</difficult><bndbox><xmin>438</xmin><ymin>65</ymin><xmax>739</xmax><ymax>136</ymax></bndbox><confidence>0.9614</confidence></object><object><name>ayat_line</name><pose>Unspecified</pose><truncated>0</truncated><difficult>0</difficult><bndbox><xmin>282</xmin><ymin>206</ymin><xmax>619</xmax><ymax>275</ymax></bndbox><confidence>0.9573</confidence></object><object><name>ayat_line</name><pose>Unspecified</pose><truncated>0</truncated><difficult>0</difficult><bndbox><xmin>618</xmin><ymin>136</ymin><xmax>739</xmax><ymax>205</ymax></bndbox><confidence>0.9567</confidence></object><object><name>ayat_line</name><pose>Unspecified</pose><truncated>0</truncated><difficult>0</difficult><bndbox><xmin>290</xmin><ymin>1046</ymin><xmax>520</xmax><ymax>1118</ymax></bndbox><confidence>0.9562</confidence></object><object><name>ayat_line</name><pose>Unspecified</pose><truncated>0</truncated><difficult>0</difficult><bndbox><xmin>68</xmin><ymin>65</ymin><xmax>214</xmax><ymax>136</ymax></bndbox><confidence>0.9526</confidence></object><object><name>ayat_line</name><pose>Unspecified</pose><truncated>0</truncated><difficult>0</difficult><bndbox><xmin>67</xmin><ymin>1046</ymin><xmax>290</xmax><ymax>1118</ymax></bndbox><confidence>0.9525</confidence></object><object><name>ayat_line</name><pose>Unspecified</pose><truncated>0</truncated><difficult>0</difficult><bndbox><xmin>620</xmin><ymin>205</ymin><xmax>739</xmax><ymax>275</ymax></bndbox><confidence>0.9466</confidence></object><object><name>ayat_line</name><pose>Unspecified</pose><truncated>0</truncated><difficult>0</difficult><bndbox><xmin>608</xmin><ymin>556</ymin><xmax>740</xmax><ymax>626</ymax></bndbox><confidence>0.9446</confidence></object><object><name>ayat_line</name><pose>Unspecified</pose><truncated>0</truncated><difficult>0</difficult><bndbox><xmin>690</xmin><ymin>627</ymin><xmax>739</xmax><ymax>697</ymax></bndbox><confidence>0.9435</confidence></object><object><name>ayah_marker</name><pose>Unspecified</pose><truncated>0</truncated><difficult>0</difficult><bndbox><xmin>370</xmin><ymin>505</ymin><xmax>407</xmax><ymax>547</ymax></bndbox><confidence>0.9279</confidence></object><object><name>ayah_marker</name><pose>Unspecified</pose><truncated>0</truncated><difficult>0</difficult><bndbox><xmin>79</xmin><ymin>991</ymin><xmax>116</xmax><ymax>1032</ymax></bndbox><confidence>0.9258</confidence></object><object><name>ayah_marker</name><pose>Unspecified</pose><truncated>0</truncated><difficult>0</difficult><bndbox><xmin>421</xmin><ymin>711</ymin><xmax>458</xmax><ymax>753</ymax></bndbox><confidence>0.9245</confidence></object><object><name>ayah_marker</name><pose>Unspecified</pose><truncated>0</truncated><difficult>0</difficult><bndbox><xmin>291</xmin><ymin>1060</ymin><xmax>328</xmax><ymax>1102</ymax></bndbox><confidence>0.9241</confidence></object><object><name>ayah_marker</name><pose>Unspecified</pose><truncated>0</truncated><difficult>0</difficult><bndbox><xmin>359</xmin><ymin>154</ymin><xmax>396</xmax><ymax>195</ymax></bndbox><confidence>0.9227</confidence></object><object><name>ayah_marker</name><pose>Unspecified</pose><truncated>0</truncated><difficult>0</difficult><bndbox><xmin>216</xmin><ymin>85</ymin><xmax>252</xmax><ymax>126</ymax></bndbox><confidence>0.9216</confidence></object><object><name>ayah_marker</name><pose>Unspecified</pose><truncated>0</truncated><difficult>0</difficult><bndbox><xmin>521</xmin><ymin>1060</ymin><xmax>557</xmax><ymax>1100</ymax></bndbox><confidence>0.9215</confidence></object><object><name>ayah_marker</name><pose>Unspecified</pose><truncated>0</truncated><difficult>0</difficult><bndbox><xmin>283</xmin><ymin>223</ymin><xmax>319</xmax><ymax>264</ymax></bndbox><confidence>0.9210</confidence></object><object><name>ayah_marker</name><pose>Unspecified</pose><truncated>0</truncated><difficult>0</difficult><bndbox><xmin>619</xmin><ymin>155</ymin><xmax>655</xmax><ymax>197</ymax></bndbox><confidence>0.9199</confidence></object><object><name>ayah_marker</name><pose>Unspecified</pose><truncated>0</truncated><difficult>0</difficult><bndbox><xmin>502</xmin><ymin>990</ymin><xmax>538</xmax><ymax>1032</ymax></bndbox><confidence>0.9192</confidence></object><object><name>ayah_marker</name><pose>Unspecified</pose><truncated>0</truncated><difficult>0</difficult><bndbox><xmin>79</xmin><ymin>644</ymin><xmax>116</xmax><ymax>685</ymax></bndbox><confidence>0.9190</confidence></object><object><name>ayah_marker</name><pose>Unspecified</pose><truncated>0</truncated><difficult>0</difficult><bndbox><xmin>81</xmin><ymin>435</ymin><xmax>117</xmax><ymax>476</ymax></bndbox><confidence>0.9189</confidence></object><object><name>ayah_marker</name><pose>Unspecified</pose><truncated>0</truncated><difficult>0</difficult><bndbox><xmin>439</xmin><ymin>85</ymin><xmax>475</xmax><ymax>126</ymax></bndbox><confidence>0.9178</confidence></object><object><name>ayah_marker</name><pose>Unspecified</pose><truncated>0</truncated><difficult>0</difficult><bndbox><xmin>83</xmin><ymin>708</ymin><xmax>119</xmax><ymax>749</ymax></bndbox><confidence>0.9175</confidence></object><object><name>ayah_marker</name><pose>Unspecified</pose><truncated>0</truncated><difficult>0</difficult><bndbox><xmin>364</xmin><ymin>437</ymin><xmax>401</xmax><ymax>478</ymax></bndbox><confidence>0.9174</confidence></object><object><name>ayah_marker</name><pose>Unspecified</pose><truncated>0</truncated><difficult>0</difficult><bndbox><xmin>316</xmin><ymin>574</ymin><xmax>353</xmax><ymax>615</ymax></bndbox><confidence>0.9168</confidence></object><object><name>ayah_marker</name><pose>Unspecified</pose><truncated>0</truncated><difficult>0</difficult><bndbox><xmin>81</xmin><ymin>921</ymin><xmax>117</xmax><ymax>963</ymax></bndbox><confidence>0.9166</confidence></object><object><name>ayah_marker</name><pose>Unspecified</pose><truncated>0</truncated><difficult>0</difficult><bndbox><xmin>621</xmin><ymin>224</ymin><xmax>657</xmax><ymax>265</ymax></bndbox><confidence>0.9164</confidence></object><object><name>ayah_marker</name><pose>Unspecified</pose><truncated>0</truncated><difficult>0</difficult><bndbox><xmin>386</xmin><ymin>644</ymin><xmax>423</xmax><ymax>685</ymax></bndbox><confidence>0.9163</confidence></object><object><name>ayah_marker</name><pose>Unspecified</pose><truncated>0</truncated><difficult>0</difficult><bndbox><xmin>82</xmin><ymin>224</ymin><xmax>118</xmax><ymax>265</ymax></bndbox><confidence>0.9158</confidence></object><object><name>ayah_marker</name><pose>Unspecified</pose><truncated>0</truncated><difficult>0</difficult><bndbox><xmin>301</xmin><ymin>990</ymin><xmax>336</xmax><ymax>1031</ymax></bndbox><confidence>0.9149</confidence></object><object><name>ayah_marker</name><pose>Unspecified</pose><truncated>0</truncated><difficult>0</difficult><bndbox><xmin>580</xmin><ymin>438</ymin><xmax>618</xmax><ymax>479</ymax></bndbox><confidence>0.9146</confidence></object><object><name>ayah_marker</name><pose>Unspecified</pose><truncated>0</truncated><difficult>0</difficult><bndbox><xmin>609</xmin><ymin>575</ymin><xmax>646</xmax><ymax>616</ymax></bndbox><confidence>0.9144</confidence></object><object><name>ayah_marker</name><pose>Unspecified</pose><truncated>0</truncated><difficult>0</difficult><bndbox><xmin>79</xmin><ymin>1060</ymin><xmax>115</xmax><ymax>1101</ymax></bndbox><confidence>0.9141</confidence></object><object><name>ayah_marker</name><pose>Unspecified</pose><truncated>0</truncated><difficult>0</difficult><bndbox><xmin>398</xmin><ymin>923</ymin><xmax>435</xmax><ymax>965</ymax></bndbox><confidence>0.9069</confidence></object><object><name>ayah_marker</name><pose>Unspecified</pose><truncated>0</truncated><difficult>0</difficult><bndbox><xmin>691</xmin><ymin>645</ymin><xmax>728</xmax><ymax>686</ymax></bndbox><confidence>0.8965</confidence></object></annotation>