<?xml version='1.0' encoding='utf-8'?>
<annotation verified="no"><folder>images</folder><filename>quba-page_206.jpg</filename><path>/Users/syaamil/development/Quran-Bounding/quran-bounding-project/experiments/model-v1/images/quba-page_206.jpg</path><source><database>Unknown</database></source><size><width>814</width><height>1169</height><depth>3</depth></size><segmented>0</segmented><object><name>ayat_line</name><pose>Unspecified</pose><truncated>0</truncated><difficult>0</difficult><bndbox><xmin>68</xmin><ymin>65</ymin><xmax>738</xmax><ymax>276</ymax></bndbox><confidence>0.9801</confidence></object><object><name>ayat_line</name><pose>Unspecified</pose><truncated>0</truncated><difficult>0</difficult><bndbox><xmin>69</xmin><ymin>976</ymin><xmax>738</xmax><ymax>1119</ymax></bndbox><confidence>0.9685</confidence></object><object><name>ayat_line</name><pose>Unspecified</pose><truncated>0</truncated><difficult>0</difficult><bndbox><xmin>68</xmin><ymin>907</ymin><xmax>552</xmax><ymax>977</ymax></bndbox><confidence>0.9656</confidence></object><object><name>ayat_line</name><pose>Unspecified</pose><truncated>0</truncated><difficult>0</difficult><bndbox><xmin>69</xmin><ymin>766</ymin><xmax>697</xmax><ymax>836</ymax></bndbox><confidence>0.9614</confidence></object><object><name>ayat_line</name><pose>Unspecified</pose><truncated>0</truncated><difficult>0</difficult><bndbox><xmin>68</xmin><ymin>836</ymin><xmax>741</xmax><ymax>907</ymax></bndbox><confidence>0.9613</confidence></object><object><name>ayat_line</name><pose>Unspecified</pose><truncated>0</truncated><difficult>0</difficult><bndbox><xmin>68</xmin><ymin>276</ymin><xmax>588</xmax><ymax>346</ymax></bndbox><confidence>0.9600</confidence></object><object><name>ayat_line</name><pose>Unspecified</pose><truncated>0</truncated><difficult>0</difficult><bndbox><xmin>69</xmin><ymin>346</ymin><xmax>535</xmax><ymax>415</ymax></bndbox><confidence>0.9578</confidence></object><object><name>ayat_line</name><pose>Unspecified</pose><truncated>0</truncated><difficult>0</difficult><bndbox><xmin>552</xmin><ymin>908</ymin><xmax>739</xmax><ymax>977</ymax></bndbox><confidence>0.9576</confidence></object><object><name>ayat_line</name><pose>Unspecified</pose><truncated>0</truncated><difficult>0</difficult><bndbox><xmin>535</xmin><ymin>346</ymin><xmax>738</xmax><ymax>416</ymax></bndbox><confidence>0.9566</confidence></object><object><name>ayat_line</name><pose>Unspecified</pose><truncated>0</truncated><difficult>0</difficult><bndbox><xmin>588</xmin><ymin>276</ymin><xmax>738</xmax><ymax>346</ymax></bndbox><confidence>0.9554</confidence></object><object><name>ayat_line</name><pose>Unspecified</pose><truncated>0</truncated><difficult>0</difficult><bndbox><xmin>69</xmin><ymin>414</ymin><xmax>738</xmax><ymax>766</ymax></bndbox><confidence>0.9511</confidence></object><object><name>ayah_marker</name><pose>Unspecified</pose><truncated>0</truncated><difficult>0</difficult><bndbox><xmin>86</xmin><ymin>1060</ymin><xmax>123</xmax><ymax>1102</ymax></bndbox><confidence>0.9349</confidence></object><object><name>ayat_line</name><pose>Unspecified</pose><truncated>0</truncated><difficult>0</difficult><bndbox><xmin>694</xmin><ymin>766</ymin><xmax>738</xmax><ymax>836</ymax></bndbox><confidence>0.9338</confidence></object><object><name>ayah_marker</name><pose>Unspecified</pose><truncated>0</truncated><difficult>0</difficult><bndbox><xmin>536</xmin><ymin>365</ymin><xmax>573</xmax><ymax>407</ymax></bndbox><confidence>0.9269</confidence></object><object><name>ayah_marker</name><pose>Unspecified</pose><truncated>0</truncated><difficult>0</difficult><bndbox><xmin>696</xmin><ymin>784</ymin><xmax>733</xmax><ymax>826</ymax></bndbox><confidence>0.9240</confidence></object><object><name>ayah_marker</name><pose>Unspecified</pose><truncated>0</truncated><difficult>0</difficult><bndbox><xmin>590</xmin><ymin>297</ymin><xmax>628</xmax><ymax>339</ymax></bndbox><confidence>0.9223</confidence></object><object><name>ayah_marker</name><pose>Unspecified</pose><truncated>0</truncated><difficult>0</difficult><bndbox><xmin>571</xmin><ymin>927</ymin><xmax>608</xmax><ymax>970</ymax></bndbox><confidence>0.9209</confidence></object></annotation>